libppocr/__init__.py
libppocr/core_tokenizers.dll
libppocr/fastdeploy.dll
libppocr/icudt70.dll
libppocr/icuuc70.dll
libppocr/libppocr.dll
libppocr/onnxruntime.dll
libppocr/onnxruntime_providers_shared.dll
libppocr/opencv_world3416.dll
libppocr/paddle2onnx.dll
libppocr/ppocr.py
libppocr/test_dll.py
libppocr/yaml-cpp.dll
libppocr/models/ppocr_keys_v1.txt
libppocr/models/ch_PP-OCRv3_det_infer/inference.pdiparams
libppocr/models/ch_PP-OCRv3_det_infer/inference.pdiparams.info
libppocr/models/ch_PP-OCRv3_det_infer/inference.pdmodel
libppocr/models/ch_PP-OCRv3_rec_infer/inference.pdiparams
libppocr/models/ch_PP-OCRv3_rec_infer/inference.pdiparams.info
libppocr/models/ch_PP-OCRv3_rec_infer/inference.pdmodel
libppocr/models/ch_PP-OCRv4_det_infer/inference.pdiparams
libppocr/models/ch_PP-OCRv4_det_infer/inference.pdiparams.info
libppocr/models/ch_PP-OCRv4_det_infer/inference.pdmodel
libppocr/models/ch_PP-OCRv4_rec_infer/inference.pdiparams
libppocr/models/ch_PP-OCRv4_rec_infer/inference.pdiparams.info
libppocr/models/ch_PP-OCRv4_rec_infer/inference.pdmodel
libppocr/models/ch_ppocr_mobile_v2.0_cls_infer/._inference.pdmodel
libppocr/models/ch_ppocr_mobile_v2.0_cls_infer/inference.pdiparams
libppocr/models/ch_ppocr_mobile_v2.0_cls_infer/inference.pdiparams.info
libppocr/models/ch_ppocr_mobile_v2.0_cls_infer/inference.pdmodel
libppocr-0.4.1.dist-info/METADATA
libppocr-0.4.1.dist-info/WHEEL
libppocr-0.4.1.dist-info/top_level.txt
libppocr-0.4.1.dist-info/RECORD
